oauth2client/__init__.py
oauth2client/_helpers.py
oauth2client/_openssl_crypt.py
oauth2client/_pkce.py
oauth2client/_pure_python_crypt.py
oauth2client/_pycrypto_crypt.py
oauth2client/client.py
oauth2client/clientsecrets.py
oauth2client/crypt.py
oauth2client/file.py
oauth2client/service_account.py
oauth2client/tools.py
oauth2client/transport.py
oauth2client/contrib/__init__.py
oauth2client/contrib/_appengine_ndb.py
oauth2client/contrib/_metadata.py
oauth2client/contrib/appengine.py
oauth2client/contrib/devshell.py
oauth2client/contrib/dictionary_storage.py
oauth2client/contrib/flask_util.py
oauth2client/contrib/gce.py
oauth2client/contrib/keyring_storage.py
oauth2client/contrib/multiprocess_file_storage.py
oauth2client/contrib/sqlalchemy.py
oauth2client/contrib/xsrfutil.py
oauth2client/contrib/django_util/__init__.py
oauth2client/contrib/django_util/apps.py
oauth2client/contrib/django_util/decorators.py
oauth2client/contrib/django_util/models.py
oauth2client/contrib/django_util/signals.py
oauth2client/contrib/django_util/site.py
oauth2client/contrib/django_util/storage.py
oauth2client/contrib/django_util/views.py
internationaltouch_oauth2client-4.1.6.dist-info/LICENSE
internationaltouch_oauth2client-4.1.6.dist-info/METADATA
internationaltouch_oauth2client-4.1.6.dist-info/WHEEL
internationaltouch_oauth2client-4.1.6.dist-info/top_level.txt
internationaltouch_oauth2client-4.1.6.dist-info/RECORD
