Metadata-Version: 2.1
Name: internationaltouch-oauth2client
Version: 4.1.6
Summary: OAuth 2.0 client library
Home-page: http://github.com/google/oauth2client/
Author: Google Inc.
Author-email: jonwayne+oauth2client@google.com
License: Apache 2.0
Keywords: google oauth 2.0 http client
Classifier: Programming Language :: Python :: 3.6
Classifier: Development Status :: 7 - Inactive
Classifier: Intended Audience :: Developers
Classifier: License :: OSI Approved :: Apache Software License
Classifier: Operating System :: POSIX
Classifier: Topic :: Internet :: WWW/HTTP
Requires-Python: >=3.6
License-File: LICENSE
Requires-Dist: httplib2 >=0.9.1
Requires-Dist: pyasn1 >=0.1.7
Requires-Dist: pyasn1-modules >=0.0.5
Requires-Dist: rsa >=3.1.4
Requires-Dist: six >=1.6.1
